pokeapiclient/__init__.py
pokeapiclient/api_client.py
pokeapiclient/api_response.py
pokeapiclient/configuration.py
pokeapiclient/exceptions.py
pokeapiclient/py.typed
pokeapiclient/rest.py
pokeapiclient/api/__init__.py
pokeapiclient/api/ability_api.py
pokeapiclient/api/berry_api.py
pokeapiclient/api/berry_firmness_api.py
pokeapiclient/api/berry_flavor_api.py
pokeapiclient/api/characteristic_api.py
pokeapiclient/api/contest_effect_api.py
pokeapiclient/api/contest_type_api.py
pokeapiclient/api/egg_group_api.py
pokeapiclient/api/encounter_condition_api.py
pokeapiclient/api/encounter_condition_value_api.py
pokeapiclient/api/encounter_method_api.py
pokeapiclient/api/evolution_chain_api.py
pokeapiclient/api/evolution_trigger_api.py
pokeapiclient/api/gender_api.py
pokeapiclient/api/generation_api.py
pokeapiclient/api/growth_rate_api.py
pokeapiclient/api/item_api.py
pokeapiclient/api/item_attribute_api.py
pokeapiclient/api/item_category_api.py
pokeapiclient/api/item_fling_effect_api.py
pokeapiclient/api/item_pocket_api.py
pokeapiclient/api/language_api.py
pokeapiclient/api/location_api.py
pokeapiclient/api/location_area_api.py
pokeapiclient/api/machine_api.py
pokeapiclient/api/move_ailment_api.py
pokeapiclient/api/move_api.py
pokeapiclient/api/move_battle_style_api.py
pokeapiclient/api/move_category_api.py
pokeapiclient/api/move_damage_class_api.py
pokeapiclient/api/move_learn_method_api.py
pokeapiclient/api/move_target_api.py
pokeapiclient/api/nature_api.py
pokeapiclient/api/pal_park_area_api.py
pokeapiclient/api/pokeathlon_stat_api.py
pokeapiclient/api/pokedex_api.py
pokeapiclient/api/pokemon_api.py
pokeapiclient/api/pokemon_color_api.py
pokeapiclient/api/pokemon_form_api.py
pokeapiclient/api/pokemon_habitat_api.py
pokeapiclient/api/pokemon_shape_api.py
pokeapiclient/api/pokemon_species_api.py
pokeapiclient/api/region_api.py
pokeapiclient/api/stat_api.py
pokeapiclient/api/super_contest_effect_api.py
pokeapiclient/api/type_api.py
pokeapiclient/api/version_api.py
pokeapiclient-1.2.0.dist-info/METADATA
pokeapiclient-1.2.0.dist-info/WHEEL
pokeapiclient-1.2.0.dist-info/top_level.txt
pokeapiclient-1.2.0.dist-info/RECORD
